fk7py/FK7Python.py
fk7py/__init__.py
fk7py/cli.py
fk7py-0.1.2.dist-info/licenses/LICENSE
fk7py-0.1.2.dist-info/METADATA
fk7py-0.1.2.dist-info/WHEEL
fk7py-0.1.2.dist-info/entry_points.txt
fk7py-0.1.2.dist-info/top_level.txt
fk7py-0.1.2.dist-info/RECORD
