Metadata-Version: 2.4
Name: fk7py
Version: 0.1.2
Summary: Pacote para trabalhar com arquivos FK7 de medidores de energia elétrica.
Author-email: Bruno Oliveira <bruno.sowk@gmail.com>
License: Apache-2.0
Project-URL: Github, https://github.com/bruno-so25/fk7py
Classifier: Programming Language :: Python :: 3
Classifier: License :: OSI Approved :: Apache Software License
Classifier: Intended Audience :: Developers
Classifier: Topic :: Utilities
Classifier: Development Status :: 3 - Alpha
Requires-Python: >=3.6
License-File: LICENSE
Dynamic: license-file
